LICENSE
MANIFEST.in
README.md
setup.cfg
setup.py
./aedir_pproc/__about__.py
./aedir_pproc/__init__.py
./aedir_pproc/cron.py
./aedir_pproc/groups.py
./aedir_pproc/pwsync.py
./aedir_pproc/update.py
./aedir_pproc/pwd/__init__.py
./aedir_pproc/pwd/cron.py
./aedir_pproc/pwd/expreset.py
./aedir_pproc/pwd/expwarn.py
./aedir_pproc/pwd/welcome.py
./aedir_pproc/pwd/web/__init__.py
./aedir_pproc/pwd/web/app.py
./aedir_pproc/pwd/web/forms.py
./aedir_pproc/pwd/web/settings.py
./aedir_pproc/pwd/web/views.py
ae_dir_pproc.egg-info/PKG-INFO
ae_dir_pproc.egg-info/SOURCES.txt
ae_dir_pproc.egg-info/dependency_links.txt
ae_dir_pproc.egg-info/not-zip-safe
ae_dir_pproc.egg-info/requires.txt
ae_dir_pproc.egg-info/top_level.txt